Metadata-Version: 2.1
Name: donationalerts
Version: 1.0.1
Summary: Handling your donation in real time
Home-page: https://github.com/cxldxice/donationalerts
Author: cxldxice
Author-email: cxldxfxtxre@gmail.com
License: MIT
Keywords: donation,handlers,alerts
Platform: UNKNOWN
